cqwu/__init__.py
cqwu/client.py
cqwu/enums/__init__.py
cqwu/errors/__init__.py
cqwu/errors/auth.py
cqwu/errors/base.py
cqwu/errors/epay.py
cqwu/methods/__init__.py
cqwu/methods/auth/__init__.py
cqwu/methods/auth/check_captcha.py
cqwu/methods/auth/export_cookie_to_file.py
cqwu/methods/auth/login.py
cqwu/methods/auth/login_with_cookie.py
cqwu/methods/auth/login_with_cookie_file.py
cqwu/methods/auth/login_with_password.py
cqwu/methods/auth/oauth.py
cqwu/methods/epay/__init__.py
cqwu/methods/epay/gen_pay_qrcode.py
cqwu/methods/epay/get_balance.py
cqwu/methods/epay/get_pay_bill.py
cqwu/methods/users/__init__.py
cqwu/methods/users/get_me.py
cqwu/methods/webvpn/__init__.py
cqwu/methods/webvpn/get_calendar.py
cqwu/methods/webvpn/get_calendar_change.py
cqwu/methods/webvpn/login_webvpn.py
cqwu/methods/xg/__init__.py
cqwu/methods/xg/get_cp.py
cqwu/methods/xg/get_public_cp.py
cqwu/methods/xg/get_score.py
cqwu/types/__init__.py
cqwu/types/calendar.py
cqwu/types/cp.py
cqwu/types/epay.py
cqwu/types/score.py
cqwu/types/user.py
cqwu/utils/__init__.py
cqwu/utils/auth.py
cqwu-0.0.10.dist-info/LICENSE
cqwu-0.0.10.dist-info/METADATA
cqwu-0.0.10.dist-info/WHEEL
cqwu-0.0.10.dist-info/top_level.txt
cqwu-0.0.10.dist-info/RECORD
