Metadata-Version: 2.1
Name: cqwu
Version: 0.0.10
Summary: A cqwu ehall client.
Home-page: https://github.com/cqwu-ehall/cqwu-ehall
Author: omg-xtao
Author-email: xtao@xtaolink.cn
Classifier: Programming Language :: Python :: 3
Classifier: License :: OSI Approved :: MIT License
Classifier: Operating System :: OS Independent
Requires-Python: >=3.8
License-File: LICENSE
